{
  "project_info": {
    "project_number": "635690663988",
    "project_id": "nairaverse-a6b88",
    "storage_bucket": "nairaverse-a6b88.appspot.com"
  },
  "client": [
    {
      "client_info": {
        "mobilesdk_app_id": "1:635690663988:android:45d3fef0f04e87d7d88a61",
        "android_client_info": {
          "package_name": "com.example.nairaverse"
        }
      },
      "oauth_client": [],
      "api_key": [
        {
          "current_key": "AIzaSyAqbyZ_R06jttLIDi80b2kMV0pATRSw3ls"
        }
      ],
      "services": {
        "appinvite_service": {
          "other_platform_oauth_client": []
        }
      }
    }
  ],
  "configuration_version": "1"
}